pyNFFT3/NFCT.py
pyNFFT3/NFFT.py
pyNFFT3/NFMT.py
pyNFFT3/NFST.py
pyNFFT3/__init__.py
pyNFFT3/fastsum.py
pyNFFT3/flags.py
pyNFFT3/lib/AVX/libfastsumjulia.dll
pyNFFT3/lib/AVX/libfastsumjulia.dylib
pyNFFT3/lib/AVX/libnfctjulia.dll
pyNFFT3/lib/AVX/libnfctjulia.dylib
pyNFFT3/lib/AVX/libnfftjulia.dll
pyNFFT3/lib/AVX/libnfftjulia.dylib
pyNFFT3/lib/AVX/libnfstjulia.dll
pyNFFT3/lib/AVX/libnfstjulia.dylib
pyNFFT3/lib/AVX/glibc2.22/libfastsumjulia.so
pyNFFT3/lib/AVX/glibc2.22/libnfctjulia.so
pyNFFT3/lib/AVX/glibc2.22/libnfftjulia.so
pyNFFT3/lib/AVX/glibc2.22/libnfstjulia.so
pyNFFT3/lib/AVX/glibc2.40/libfastsumjulia.so
pyNFFT3/lib/AVX/glibc2.40/libnfctjulia.so
pyNFFT3/lib/AVX/glibc2.40/libnfftjulia.so
pyNFFT3/lib/AVX/glibc2.40/libnfstjulia.so
pyNFFT3/lib/AVX2/libfastsumjulia.dll
pyNFFT3/lib/AVX2/libfastsumjulia.dylib
pyNFFT3/lib/AVX2/libnfctjulia.dll
pyNFFT3/lib/AVX2/libnfctjulia.dylib
pyNFFT3/lib/AVX2/libnfftjulia.dll
pyNFFT3/lib/AVX2/libnfftjulia.dylib
pyNFFT3/lib/AVX2/libnfstjulia.dll
pyNFFT3/lib/AVX2/libnfstjulia.dylib
pyNFFT3/lib/AVX2/glibc2.22/libfastsumjulia.so
pyNFFT3/lib/AVX2/glibc2.22/libnfctjulia.so
pyNFFT3/lib/AVX2/glibc2.22/libnfftjulia.so
pyNFFT3/lib/AVX2/glibc2.22/libnfstjulia.so
pyNFFT3/lib/AVX2/glibc2.40/libfastsumjulia.so
pyNFFT3/lib/AVX2/glibc2.40/libnfctjulia.so
pyNFFT3/lib/AVX2/glibc2.40/libnfftjulia.so
pyNFFT3/lib/AVX2/glibc2.40/libnfstjulia.so
pyNFFT3/lib/SSE2/libfastsumjulia.dll
pyNFFT3/lib/SSE2/libfastsumjulia.dylib
pyNFFT3/lib/SSE2/libnfctjulia.dll
pyNFFT3/lib/SSE2/libnfctjulia.dylib
pyNFFT3/lib/SSE2/libnfftjulia.dll
pyNFFT3/lib/SSE2/libnfftjulia.dylib
pyNFFT3/lib/SSE2/libnfstjulia.dll
pyNFFT3/lib/SSE2/libnfstjulia.dylib
pyNFFT3/lib/SSE2/glibc2.22/libfastsumjulia.so
pyNFFT3/lib/SSE2/glibc2.22/libnfctjulia.so
pyNFFT3/lib/SSE2/glibc2.22/libnfftjulia.so
pyNFFT3/lib/SSE2/glibc2.22/libnfstjulia.so
pyNFFT3/lib/SSE2/glibc2.40/libfastsumjulia.so
pyNFFT3/lib/SSE2/glibc2.40/libnfctjulia.so
pyNFFT3/lib/SSE2/glibc2.40/libnfftjulia.so
pynfft3-0.2.2.dist-info/METADATA
pynfft3-0.2.2.dist-info/WHEEL
pynfft3-0.2.2.dist-info/licenses/LICENSE
pynfft3-0.2.2.dist-info/RECORD
