Metadata-Version: 2.3
Name: pyNFFT3
Version: 0.2.2
Summary: Python interface for the NFFT C library
Project-URL: Homepage, https://github.com/NFFT/pyNFFT3
Author-email: Michael Nolander <nolander.michael@gmail.com>
License-File: LICENSE
Requires-Python: >=3.8
Requires-Dist: numpy>=2.0.0
Requires-Dist: packaging>=24.1
Requires-Dist: py-cpuinfo>=9.0.0
